pybriiv/__init__.py
pybriiv/api.py
pybriiv/commands.py
pybriiv/exceptions.py
pybriiv-0.1.1.dist-info/licenses/LICENSE
tests/__init__.py
tests/test_api.py
tests/test_commands.py
pybriiv-0.1.1.dist-info/METADATA
pybriiv-0.1.1.dist-info/WHEEL
pybriiv-0.1.1.dist-info/top_level.txt
pybriiv-0.1.1.dist-info/RECORD
