Metadata-Version: 2.4
Name: pybriiv
Version: 0.1.1
Summary: Python library for communicating with Briiv Air Purifier devices
Home-page: https://github.com/FiveCreate/pybriiv
Author: FiveCreate
Author-email: support@fivecreate.co.uk
Project-URL: Bug Tracker, https://github.com/FiveCreate/pybriiv/issues
Project-URL: Documentation, https://github.com/FiveCreate/pybriiv
Project-URL: Source Code, https://github.com/FiveCreate/pybriiv
Classifier: Programming Language :: Python :: 3
Classifier: License :: OSI Approved :: MIT License
Classifier: Operating System :: OS Independent
Classifier: Development Status :: 4 - Beta
Classifier: Intended Audience :: Developers
Classifier: Topic :: Home Automation
Requires-Python: >=3.9
License-File: LICENSE
Dynamic: author
Dynamic: author-email
Dynamic: classifier
Dynamic: description
Dynamic: description-content-type
Dynamic: home-page
Dynamic: license-file
Dynamic: project-url
Dynamic: requires-python
Dynamic: summary
